{
  "54be107f-dfec-4036-8d7d-b82fa79a4176": {
    "connectionRef": {
      "apiTier": "Premium",
      "displayName": "Shadify (Independent Publisher)",
      "iconUri": "https://connectoricons-prod.azureedge.net/releases/v1.0.1631/1.0.1631.3268/shadifyip/icon.png",
      "id": "/providers/microsoft.powerapps/apis/shared_shadifyip",
      "parameterHints": {},
      "parameterHintsV2": {}
    },
    "datasets": {},
    "dataSources": [
      "Shadify(IndependentPublisher)"
    ],
    "dependencies": {},
    "dependents": [],
    "id": "54be107f-dfec-4036-8d7d-b82fa79a4176"
  }
}