{
  "205b3612-d2f3-4b63-b882-ffc37c7852b1": {
    "connectionParameters": {
      "sku": "Enterprise"
    },
    "connectionRef": {
      "displayName": "InstagramPost",
      "iconUri": "https://az787822.vo.msecnd.net/defaulticons/api-dedicated.png",
      "id": "/providers/microsoft.powerapps/apis/shared_cr715-5finstagrampost-5f70b18ed495d69cb6"
    },
    "datasets": {},
    "dataSources": [
      "Instagram"
    ],
    "dependencies": {},
    "dependents": [],
    "id": "205b3612-d2f3-4b63-b882-ffc37c7852b1"
  }
}