{
  "ComponentAllowCustomization": true,
  "ComponentChangedSinceFileImport": true,
  "ComponentDefinitionInfo": {
    "AllowAccessToGlobals": false,
    "Children": [
      {
        "AllowAccessToGlobals": true,
        "Children": [],
        "ControlPropertyState": [
          "DisplayMode",
          "DisabledFill",
          "Font",
          "Color",
          "Fill",
          "BorderColor",
          "DisabledBorderColor",
          "PressedBorderColor",
          "HoverBorderColor",
          "BorderStyle",
          {
            "AFDDataSourceName": "",
            "AutoRuleBindingEnabled": false,
            "AutoRuleBindingString": "350",
            "InvariantPropertyName": "Width",
            "IsLockable": false,
            "NameMapSourceSchema": "?"
          },
          {
            "AFDDataSourceName": "",
            "AutoRuleBindingEnabled": false,
            "AutoRuleBindingString": "110",
            "InvariantPropertyName": "Height",
            "IsLockable": false,
            "NameMapSourceSchema": "?"
          },
          "X",
          "Y",
          "ZIndex",
          {
            "AFDDataSourceName": "",
            "AutoRuleBindingEnabled": false,
            "AutoRuleBindingString": "\"Show your <b><font color=blue>HTML</font></b> text here.\"",
            "InvariantPropertyName": "HtmlText",
            "IsLockable": false,
            "NameMapSourceSchema": "?"
          },
          {
            "AFDDataSourceName": "",
            "AutoRuleBindingEnabled": false,
            "AutoRuleBindingString": "",
            "InvariantPropertyName": "PaddingTop",
            "IsLockable": false,
            "NameMapSourceSchema": "?"
          },
          {
            "AFDDataSourceName": "",
            "AutoRuleBindingEnabled": false,
            "AutoRuleBindingString": "",
            "InvariantPropertyName": "PaddingRight",
            "IsLockable": false,
            "NameMapSourceSchema": "?"
          },
          {
            "AFDDataSourceName": "",
            "AutoRuleBindingEnabled": false,
            "AutoRuleBindingString": "",
            "InvariantPropertyName": "PaddingBottom",
            "IsLockable": false,
            "NameMapSourceSchema": "?"
          },
          {
            "AFDDataSourceName": "",
            "AutoRuleBindingEnabled": false,
            "AutoRuleBindingString": "",
            "InvariantPropertyName": "PaddingLeft",
            "IsLockable": false,
            "NameMapSourceSchema": "?"
          },
          {
            "AFDDataSourceName": "",
            "AutoRuleBindingEnabled": false,
            "AutoRuleBindingString": "24",
            "InvariantPropertyName": "Size",
            "IsLockable": false,
            "NameMapSourceSchema": "?"
          }
        ],
        "ControlUniqueId": "6",
        "HasDynamicProperties": false,
        "Index": 0,
        "IsAutoGenerated": false,
        "IsDataControl": false,
        "IsFromScreenLayout": false,
        "IsGroupControl": false,
        "IsLocked": false,
        "LayoutName": "",
        "MetaDataIDKey": "",
        "Name": "ButtonBackground_1",
        "Parent": "Container",
        "PersistMetaDataIDKey": false,
        "PublishOrderIndex": 29,
        "Rules": [
          {
            "Category": "Data",
            "InvariantScript": "\"<div style='width: \"& Parent.Width - 30 &\"px;height: \"& Parent.Height - 30 &\"px;\r\nborder-radius: \"& Container.BorderRadius &\"px;\r\nborder: 0px solid white;\r\nmargin-left:15px;\r\nmargin-top:10px;\r\nbox-shadow: 0 4px 8px 0 rgba(0, 0, 0, 0.2), 0 6px 20px 0 rgba(0, 0, 0, 0.19);\r\nbackground: radial-gradient(ellipse at top, \"&Container.GradientColor1 &\", transparent) 40%,\r\n            radial-gradient(circle at center, \"&Container.GradientColor2 &\", transparent) 40%,\r\n            radial-gradient(ellipse at bottom,\"&Container.GradientColor3 &\", transparent)40%;\r\n'></div>\"",
            "Property": "HtmlText",
            "RuleProviderType": "Unknown"
          },
          {
            "Category": "Design",
            "InvariantScript": "Parent.Width",
            "Property": "Width",
            "RuleProviderType": "Unknown"
          },
          {
            "Category": "Design",
            "InvariantScript": "0",
            "Property": "PaddingRight",
            "RuleProviderType": "Unknown"
          },
          {
            "Category": "Design",
            "InvariantScript": "0",
            "Property": "PaddingTop",
            "RuleProviderType": "Unknown"
          },
          {
            "Category": "Design",
            "InvariantScript": "1",
            "Property": "ZIndex",
            "RuleProviderType": "Unknown"
          },
          {
            "Category": "Design",
            "InvariantScript": "0",
            "Property": "Y",
            "RuleProviderType": "Unknown"
          },
          {
            "Category": "Design",
            "InvariantScript": "0",
            "Property": "X",
            "RuleProviderType": "Unknown"
          },
          {
            "Category": "Design",
            "InvariantScript": "Parent.Height",
            "Property": "Height",
            "RuleProviderType": "Unknown"
          },
          {
            "Category": "Design",
            "InvariantScript": "0",
            "Property": "PaddingLeft",
            "RuleProviderType": "Unknown"
          },
          {
            "Category": "Design",
            "InvariantScript": "0",
            "Property": "PaddingBottom",
            "RuleProviderType": "Unknown"
          },
          {
            "Category": "Design",
            "InvariantScript": "BorderStyle.None",
            "Property": "BorderStyle",
            "RuleProviderType": "Unknown"
          },
          {
            "Category": "Design",
            "InvariantScript": "RGBA(56, 56, 56, 1)",
            "Property": "DisabledBorderColor",
            "RuleProviderType": "Unknown"
          },
          {
            "Category": "Design",
            "InvariantScript": "RGBA(0, 0, 0, 1)",
            "Property": "BorderColor",
            "RuleProviderType": "Unknown"
          },
          {
            "Category": "Design",
            "InvariantScript": "RGBA(255, 255, 255, 0)",
            "Property": "Fill",
            "RuleProviderType": "Unknown"
          },
          {
            "Category": "Design",
            "InvariantScript": "RGBA(0, 0, 0, 1)",
            "Property": "Color",
            "RuleProviderType": "Unknown"
          },
          {
            "Category": "Design",
            "InvariantScript": "Font.'Open Sans'",
            "Property": "Font",
            "RuleProviderType": "Unknown"
          },
          {
            "Category": "Design",
            "InvariantScript": "RGBA(119, 119, 119, .4)",
            "Property": "DisabledFill",
            "RuleProviderType": "Unknown"
          },
          {
            "Category": "Design",
            "InvariantScript": "DisplayMode.Edit",
            "Property": "DisplayMode",
            "RuleProviderType": "Unknown"
          },
          {
            "Category": "Design",
            "InvariantScript": "Self.BorderColor",
            "Property": "HoverBorderColor",
            "RuleProviderType": "Unknown"
          },
          {
            "Category": "Design",
            "InvariantScript": "Self.BorderColor",
            "Property": "PressedBorderColor",
            "RuleProviderType": "Unknown"
          },
          {
            "Category": "Design",
            "InvariantScript": "",
            "Property": "Size",
            "RuleProviderType": "Unknown"
          }
        ],
        "StyleName": "",
        "Template": {
          "CustomGroupControlTemplateName": "",
          "FirstParty": true,
          "Id": "http://microsoft.com/appmagic/htmlViewer",
          "IsComponentDefinition": false,
          "IsCustomGroupControlTemplate": false,
          "IsPremiumPcfControl": false,
          "LastModifiedTimestamp": "0",
          "Name": "htmlViewer",
          "OverridableProperties": {},
          "Version": "2.1.0"
        },
        "Type": "ControlInfo",
        "VariantName": ""
      }
    ],
    "ControlPropertyState": [
      "Fill",
      {
        "AFDDataSourceName": "",
        "AutoRuleBindingEnabled": false,
        "AutoRuleBindingString": "640",
        "InvariantPropertyName": "Height",
        "IsLockable": false,
        "NameMapSourceSchema": "?"
      },
      {
        "AFDDataSourceName": "",
        "AutoRuleBindingEnabled": false,
        "AutoRuleBindingString": "640",
        "InvariantPropertyName": "Width",
        "IsLockable": false,
        "NameMapSourceSchema": "?"
      },
      "X",
      "Y",
      "ZIndex",
      {
        "AFDDataSourceName": "",
        "AutoRuleBindingEnabled": false,
        "AutoRuleBindingString": "\"Text\"",
        "InvariantPropertyName": "BorderRadius",
        "IsLockable": false,
        "NameMapSourceSchema": "?"
      },
      {
        "AFDDataSourceName": "",
        "AutoRuleBindingEnabled": false,
        "AutoRuleBindingString": "\"Text\"",
        "InvariantPropertyName": "GradientColor1",
        "IsLockable": false,
        "NameMapSourceSchema": "?"
      },
      {
        "AFDDataSourceName": "",
        "AutoRuleBindingEnabled": false,
        "AutoRuleBindingString": "\"Text\"",
        "InvariantPropertyName": "GradientColor2",
        "IsLockable": false,
        "NameMapSourceSchema": "?"
      },
      {
        "AFDDataSourceName": "",
        "AutoRuleBindingEnabled": false,
        "AutoRuleBindingString": "\"Text\"",
        "InvariantPropertyName": "GradientColor3",
        "IsLockable": false,
        "NameMapSourceSchema": "?"
      }
    ],
    "LastModifiedTimestamp": "638293133683707158",
    "Name": "Container",
    "Rules": [
      {
        "Category": "Data",
        "InvariantScript": "20",
        "Property": "BorderRadius",
        "RuleProviderType": "System"
      },
      {
        "Category": "Data",
        "InvariantScript": "\"#77A1D3\"",
        "Property": "GradientColor1",
        "RuleProviderType": "System"
      },
      {
        "Category": "Data",
        "InvariantScript": "\"#076585\"",
        "Property": "GradientColor2",
        "RuleProviderType": "System"
      },
      {
        "Category": "Data",
        "InvariantScript": "\"#77A1D3\"",
        "Property": "GradientColor3",
        "RuleProviderType": "System"
      },
      {
        "Category": "Design",
        "InvariantScript": "RGBA(0, 0, 0, 0)",
        "Property": "Fill",
        "RuleProviderType": "System"
      },
      {
        "Category": "Design",
        "InvariantScript": "110",
        "Property": "Height",
        "RuleProviderType": "System"
      },
      {
        "Category": "Design",
        "InvariantScript": "450",
        "Property": "Width",
        "RuleProviderType": "System"
      },
      {
        "Category": "Design",
        "InvariantScript": "0",
        "Property": "X",
        "RuleProviderType": "System"
      },
      {
        "Category": "Design",
        "InvariantScript": "0",
        "Property": "Y",
        "RuleProviderType": "System"
      },
      {
        "Category": "Design",
        "InvariantScript": "1",
        "Property": "ZIndex",
        "RuleProviderType": "System"
      }
    ]
  },
  "ComponentManifest": {
    "AllowAccessToGlobals": false,
    "AllowCustomization": true,
    "Description": "",
    "Name": "Container",
    "TemplateGuid": "f4e5c5cc06674b07b5526e6ea336aff6"
  },
  "ComponentType": "CanvasComponent",
  "CustomGroupControlTemplateName": "",
  "CustomProperties": [
    {
      "Category": 0,
      "DisplayName": "BorderRadius",
      "Hidden": false,
      "Name": "BorderRadius",
      "PropertyDataTypeKey": "String",
      "Tooltip": "A custom property",
      "Type": "{\"Version\":\"1.334\",\"Type\":{\"Name\":\"Root\",\"Kind\":\"String\",\"EnumString\":\"\",\"Type\":[]}}"
    },
    {
      "Category": 0,
      "DisplayName": "GradientColor1",
      "Hidden": false,
      "Name": "GradientColor1",
      "PropertyDataTypeKey": "String",
      "Tooltip": "A custom property",
      "Type": "{\"Version\":\"1.334\",\"Type\":{\"Name\":\"Root\",\"Kind\":\"String\",\"EnumString\":\"\",\"Type\":[]}}"
    },
    {
      "Category": 0,
      "DisplayName": "GradientColor2",
      "Hidden": false,
      "Name": "GradientColor2",
      "PropertyDataTypeKey": "String",
      "Tooltip": "A custom property",
      "Type": "{\"Version\":\"1.334\",\"Type\":{\"Name\":\"Root\",\"Kind\":\"String\",\"EnumString\":\"\",\"Type\":[]}}"
    },
    {
      "Category": 0,
      "DisplayName": "GradientColor3",
      "Hidden": false,
      "Name": "GradientColor3",
      "PropertyDataTypeKey": "String",
      "Tooltip": "A custom property",
      "Type": "{\"Version\":\"1.334\",\"Type\":{\"Name\":\"Root\",\"Kind\":\"String\",\"EnumString\":\"\",\"Type\":[]}}"
    }
  ],
  "FirstParty": true,
  "Id": "http://microsoft.com/appmagic/Component",
  "IsComponentLocked": false,
  "IsComponentTemplate": true,
  "IsCustomGroupControlTemplate": false,
  "IsPcfControl": false,
  "IsPremiumPcfControl": false,
  "IsWidgetTemplate": false,
  "LastModifiedTimestamp": "638293133683707158",
  "Name": "f4e5c5cc06674b07b5526e6ea336aff6",
  "OverridableProperties": {},
  "TemplateOriginalName": "36bcc75e8f56434cb5c795d43ac2f582",
  "Version": "637997287641258539"
}